plntree/__init__.py
plntree/data/__init__.py
plntree/data/cMD/loader.py
plntree/data/cMD/metadata.csv
plntree/data/cMD/studies/AsnicarF_2017_species_abundance.csv
plntree/data/cMD/studies/AsnicarF_2021_species_abundance.csv
plntree/data/cMD/studies/BackhedF_2015_species_abundance.csv
plntree/data/cMD/studies/BedarfJR_2017_species_abundance.csv
plntree/data/cMD/studies/Bengtsson-PalmeJ_2015_species_abundance.csv
plntree/data/cMD/studies/BritoIL_2016_species_abundance.csv
plntree/data/cMD/studies/BrooksB_2017_species_abundance.csv
plntree/data/cMD/studies/Castro-NallarE_2015_species_abundance.csv
plntree/data/cMD/studies/ChengpingW_2017_species_abundance.csv
plntree/data/cMD/studies/ChngKR_2016_species_abundance.csv
plntree/data/cMD/studies/ChuDM_2017_species_abundance.csv
plntree/data/cMD/studies/CosteaPI_2017_species_abundance.csv
plntree/data/cMD/studies/DavidLA_2015_species_abundance.csv
plntree/data/cMD/studies/DeFilippisF_2019_species_abundance.csv
plntree/data/cMD/studies/DhakanDB_2019_species_abundance.csv
plntree/data/cMD/studies/FengQ_2015_species_abundance.csv
plntree/data/cMD/studies/FerrettiP_2018_species_abundance.csv
plntree/data/cMD/studies/FrankelAE_2017_species_abundance.csv
plntree/data/cMD/studies/GhensiP_2019_species_abundance.csv
plntree/data/cMD/studies/GopalakrishnanV_2018_species_abundance.csv
plntree/data/cMD/studies/GuptaA_2019_species_abundance.csv
plntree/data/cMD/studies/HMP_2012_species_abundance.csv
plntree/data/cMD/studies/HMP_2019_ibdmdb_species_abundance.csv
plntree/data/cMD/studies/HMP_2019_t2d_species_abundance.csv
plntree/data/cMD/studies/HallAB_2017_species_abundance.csv
plntree/data/cMD/studies/HanniganGD_2017_species_abundance.csv
plntree/data/cMD/studies/HansenLBS_2018_species_abundance.csv
plntree/data/cMD/studies/Heitz-BuschartA_2016_species_abundance.csv
plntree/data/cMD/studies/IaniroG_2022_species_abundance.csv
plntree/data/cMD/studies/IjazUZ_2017_species_abundance.csv
plntree-1.0.0.dist-info/licenses/LICENSE
plntree-1.0.0.dist-info/METADATA
plntree-1.0.0.dist-info/WHEEL
plntree-1.0.0.dist-info/top_level.txt
plntree-1.0.0.dist-info/RECORD
