Metadata-Version: 2.4
Name: plntree
Version: 1.0.0
Summary: Package implementing PLN-Tree models and TaxaPLN augmentation.
Author-email: Alexandre Chaussard <alexandre.chaussard@sorbonne-universite.fr>
Maintainer-email: Alexandre Chaussard <alexandre.chaussard@sorbonne-universite.fr>
License-Expression: MIT
Project-URL: Homepage, https://github.com/AlexandreChaussard/PLNTree-package
Project-URL: Issues, https://github.com/AlexandreChaussard/PLNTree-package/issues
Keywords: python,count,multivariate,tree,metagenomics,taxonomy,PLN
Classifier: Development Status :: 4 - Beta
Classifier: Intended Audience :: Science/Research
Classifier: Programming Language :: Python
Requires-Python: >=3.8
License-File: LICENSE
Requires-Dist: matplotlib
Requires-Dist: numpy
Requires-Dist: pandas
Requires-Dist: scipy
Requires-Dist: seaborn
Requires-Dist: torch
Requires-Dist: scikit-learn
Requires-Dist: tqdm
Requires-Dist: networkx
Dynamic: license-file
